README.md
setup.py
mljr/__init__.py
mljr/mljr.py
mljr.egg-info/PKG-INFO
mljr.egg-info/SOURCES.txt
mljr.egg-info/dependency_links.txt
mljr.egg-info/entry_points.txt
mljr.egg-info/top_level.txt